[{"__type__":"cc.SpriteFrame","content":{"name":"horoscope_7","texture":"6dNrMVVCpIZ6UPL24Ahr0C","rect":[3,11,48,26],"offset":[0.5,2],"originalSize":[53,52]}},{"__type__":"cc.SpriteFrame","content":{"name":"horoscope_8","texture":"c1H2KXeotEgL5VLc7lav/V","rect":[0,5,53,44],"offset":[0,-1],"originalSize":[53,52]}},{"__type__":"cc.SpriteFrame","content":{"name":"horoscope_12","texture":"17UaBGGZJH27iWnpnURB7h","rect":[7,6,36,39],"offset":[-1.5,0.5],"originalSize":[53,52]}},{"__type__":"cc.SpriteFrame","content":{"name":"horoscropebg","texture":"2aTWhF0N5JlZtItMnD2Fyj","rect":[0,0,126,173],"offset":[0,0],"originalSize":[126,173]}},{"__type__":"cc.SpriteFrame","content":{"name":"horoscope_3","texture":"9dUSR06lBOBLF8vp5gqa4a","rect":[8,7,37,38],"offset":[0,0],"originalSize":[53,52]}},{"__type__":"cc.SpriteFrame","content":{"name":"horoscope_2","texture":"0eMO9hTX9Ez4U34berL95G","rect":[10,4,33,45],"offset":[0,-0.5],"originalSize":[53,52]}},{"__type__":"cc.SpriteFrame","content":{"name":"horoscope_4","texture":"d6u/JxKpRNJJPzuY+7IOtU","rect":[5,6,42,41],"offset":[-0.5,-0.5],"originalSize":[53,52]}},{"__type__":"cc.SpriteFrame","content":{"name":"horoscope_5","texture":"85eIMe4uZJLI8Dy7AlHxfV","rect":[2,3,48,46],"offset":[-0.5,0],"originalSize":[53,52]}},[{"__type__":"cc.Prefab","_name":"HoroscopePage","data":{"__id__":1},"asyncLoadAssets":null},{"__type__":"cc.Node","_name":"HoroscopePage","_children":[{"__id__":2},{"__id__":3},{"__id__":4},{"__id__":5},{"__id__":6}],"_components":[{"__type__":"cc.Widget","node":{"__id__":1},"_alignFlags":45,"_originalWidth":640.1,"_originalHeight":1136},{"__type__":"cc.BlockInputEvents","node":{"__id__":1}},{"__type__":"df2df1LRrBJZbEZzJ7Zwm5E","node":{"__id__":1},"itemPrefab":{"__uuid__":"d01RGynPFEN6LW70xZpx3s"}}],"_prefab":{"__type__":"cc.PrefabInfo","root":{"__id__":1},"asset":{"__uuid__":"8c1g7rgqpJMp6xM/h/hAQn"},"fileId":"7dT8Qz/q9N/48nb7XiQbnK"},"_contentSize":{"__type__":"cc.Size","width":640,"height":1136},"_position":{"__type__":"cc.Vec2","x":320,"y":568}},{"__type__":"cc.Node","_name":"beijing","_parent":{"__id__":1},"_components":[{"__type__":"cc.Sprite","node":{"__id__":2},"_spriteFrame":{"__uuid__":"6cgDmp0VxFAaxcGSvVPMD+"},"_sizeMode":0},{"__type__":"cc.Widget","node":{"__id__":2},"_alignFlags":45,"_originalWidth":640,"_originalHeight":1138}],"_prefab":{"__type__":"cc.PrefabInfo","root":{"__id__":1},"asset":{"__uuid__":"8c1g7rgqpJMp6xM/h/hAQn"},"fileId":"4aeSFvIOxHj6QSB7ksSByU"},"_contentSize":{"__type__":"cc.Size","width":640,"height":1136}},{"__type__":"cc.Node","_name":"mask","_parent":{"__id__":1},"_components":[{"__type__":"cc.Sprite","node":{"__id__":3},"_spriteFrame":{"__uuid__":"41D7kWhyFGY7q4NDlzkazn"},"_sizeMode":0},{"__type__":"cc.Widget","node":{"__id__":3},"_alignFlags":45,"_originalWidth":640,"_originalHeight":1136}],"_prefab":{"__type__":"cc.PrefabInfo","root":{"__id__":1},"asset":{"__uuid__":"8c1g7rgqpJMp6xM/h/hAQn"},"fileId":"bdMzlydPRJOYAbdyXpVdvX"},"_opacity":150,"_color":{"__type__":"cc.Color"},"_contentSize":{"__type__":"cc.Size","width":640,"height":1136}},{"__type__":"cc.Node","_name":"fanhui","_parent":{"__id__":1},"_components":[{"__type__":"cc.Sprite","node":{"__id__":4},"_spriteFrame":{"__uuid__":"41jmlvNyVH37GXzExfJZBx"},"_sizeMode":0,"_isTrimmedMode":false},{"__type__":"cc.Button","node":{"__id__":4},"transition":3,"clickEvents":[{"__type__":"cc.ClickEvent","target":{"__id__":1},"component":"HoroscopePage","handler":"onClose"}],"_N$target":{"__id__":4}}],"_prefab":{"__type__":"cc.PrefabInfo","root":{"__id__":1},"asset":{"__uuid__":"8c1g7rgqpJMp6xM/h/hAQn"},"fileId":"43Axxdu55KVIM4+GTUceAc"},"_contentSize":{"__type__":"cc.Size","width":71,"height":78},"_position":{"__type__":"cc.Vec2","x":-271,"y":505}},{"__type__":"cc.Node","_name":"label","_parent":{"__id__":1},"_components":[{"__type__":"cc.Label","node":{"__id__":5},"_useOriginalSize":false,"_actualFontSize":80,"_fontSize":80,"_lineHeight":80,"_N$string":"Horoscope","_N$horizontalAlign":1,"_N$verticalAlign":1}],"_prefab":{"__type__":"cc.PrefabInfo","root":{"__id__":1},"asset":{"__uuid__":"8c1g7rgqpJMp6xM/h/hAQn"},"fileId":"d1cddH/doRNQ4Aodz8556bh"},"_contentSize":{"__type__":"cc.Size","width":387,"height":80},"_position":{"__type__":"cc.Vec2","y":452}},{"__type__":"cc.Node","_name":"label","_parent":{"__id__":1},"_components":[{"__type__":"cc.Label","node":{"__id__":6},"_useOriginalSize":false,"_N$string":"Choose your zodiac","_N$horizontalAlign":1,"_N$verticalAlign":1}],"_prefab":{"__type__":"cc.PrefabInfo","root":{"__id__":1},"asset":{"__uuid__":"8c1g7rgqpJMp6xM/h/hAQn"},"fileId":"d1cddH/doRNQ4Aodz8556bh"},"_contentSize":{"__type__":"cc.Size","width":354,"height":40},"_position":{"__type__":"cc.Vec2","y":380}}],{"__type__":"cc.SpriteFrame","content":{"name":"horoscope_11","texture":"63v+kD/DhHTop9rJC+YtIz","rect":[2,15,48,23],"offset":[-0.5,-0.5],"originalSize":[53,52]}},{"__type__":"cc.SpriteFrame","content":{"name":"horoscope_9","texture":"ac1k5ZIQFMyJNXjQi7JZgz","rect":[8,9,35,37],"offset":[-1,-1.5],"originalSize":[53,52]}},{"__type__":"cc.SpriteFrame","content":{"name":"horoscope_1","texture":"28i+i/zytEHr7Y0A+tg4Dy","rect":[7,7,38,39],"offset":[-0.5,-0.5],"originalSize":[53,52]}},[{"__type__":"cc.Prefab","_name":"HoroscopeItem","data":{"__id__":1},"asyncLoadAssets":null},{"__type__":"cc.Node","_name":"HoroscopeItem","_children":[{"__id__":2},{"__id__":3},{"__id__":5},{"__id__":7}],"_components":[{"__type__":"6d9d9yLUehEMr4rxmZmm9W4","node":{"__id__":1},"iconSprite":{"__id__":4},"nameLabel":{"__id__":6},"dateLabel":{"__id__":8},"frames":[{"__uuid__":"bdd+byaNJNq7H/GYZnrFti"},{"__uuid__":"56s/GdYkNHeqSevnrQ3z1J"},{"__uuid__":"44cCCEA1dDXp0sDhbxtjKq"},{"__uuid__":"87Jx4nLG1F16vy94OeYs19"},{"__uuid__":"8a/ziIWRFFIKZyVyY//Rj5"},{"__uuid__":"ffHi//j+5HE4yABhwjAQvO"},{"__uuid__":"01VU3d1AlJLaug0SpFPJtn"},{"__uuid__":"32ykqYiFxACYOw9oBliMTH"},{"__uuid__":"9f06FLvWRKDbsqM4EdHKpL"},{"__uuid__":"d18bE1gC9AKKs749VGwsBJ"},{"__uuid__":"9exTZMOWlCfr3cuZKbgENP"},{"__uuid__":"34belDckhDt4rbNOf44f64"}]},{"__type__":"cc.Button","node":{"__id__":1},"transition":3,"clickEvents":[{"__type__":"cc.ClickEvent","target":{"__id__":1},"component":"HoroscopeItem","handler":"onClick"}],"_N$target":{"__id__":1}}],"_prefab":{"__type__":"cc.PrefabInfo","root":{"__id__":1},"asset":{"__uuid__":"d01RGynPFEN6LW70xZpx3s"},"fileId":"a81DQ5OeNFeryJ2TjOKvqB"},"_contentSize":{"__type__":"cc.Size","width":126,"height":173}},{"__type__":"cc.Node","_name":"horoscropebg","_parent":{"__id__":1},"_components":[{"__type__":"cc.Sprite","node":{"__id__":2},"_spriteFrame":{"__uuid__":"42NPXm90dMCqR4NtUjWEOd"}}],"_prefab":{"__type__":"cc.PrefabInfo","root":{"__id__":1},"asset":{"__uuid__":"d01RGynPFEN6LW70xZpx3s"},"fileId":"e2tE5NVDlHy721EMU84XZd"},"_contentSize":{"__type__":"cc.Size","width":126,"height":173}},{"__type__":"cc.Node","_name":"horoscopeIcon","_parent":{"__id__":1},"_components":[{"__id__":4}],"_prefab":{"__type__":"cc.PrefabInfo","root":{"__id__":1},"asset":{"__uuid__":"d01RGynPFEN6LW70xZpx3s"},"fileId":"a2riayATpFx5Mlbs9AjCXR"},"_contentSize":{"__type__":"cc.Size","width":35,"height":37},"_position":{"__type__":"cc.Vec2","y":16.4}},{"__type__":"cc.Sprite","node":{"__id__":3},"_spriteFrame":{"__uuid__":"bdd+byaNJNq7H/GYZnrFti"}},{"__type__":"cc.Node","_name":"name","_parent":{"__id__":1},"_components":[{"__id__":6}],"_prefab":{"__type__":"cc.PrefabInfo","root":{"__id__":1},"asset":{"__uuid__":"d01RGynPFEN6LW70xZpx3s"},"fileId":"d1cddH/doRNQ4Aodz8556bh"},"_contentSize":{"__type__":"cc.Size","width":50,"height":25},"_position":{"__type__":"cc.Vec2","y":-39.4}},{"__type__":"cc.Label","node":{"__id__":5},"_useOriginalSize":false,"_actualFontSize":22,"_fontSize":22,"_lineHeight":25,"_N$string":"Aries","_N$horizontalAlign":1,"_N$verticalAlign":1},{"__type__":"cc.Node","_name":"date","_parent":{"__id__":1},"_components":[{"__id__":8}],"_prefab":{"__type__":"cc.PrefabInfo","root":{"__id__":1},"asset":{"__uuid__":"d01RGynPFEN6LW70xZpx3s"},"fileId":"00YKCL5KJPjIgxzLVtCdiM"},"_contentSize":{"__type__":"cc.Size","width":76,"height":25},"_position":{"__type__":"cc.Vec2","y":-64.5}},{"__type__":"cc.Label","node":{"__id__":7},"_useOriginalSize":false,"_actualFontSize":18,"_fontSize":18,"_lineHeight":25,"_N$string":"3/21-4/21","_N$horizontalAlign":1,"_N$verticalAlign":1}],{"__type__":"cc.SpriteFrame","content":{"name":"horoscope_10","texture":"83vpUEuHtG37//jpyXnYQX","rect":[2,5,49,42],"offset":[0,0],"originalSize":[53,52]}},{"__type__":"cc.SpriteFrame","content":{"name":"horoscope_6","texture":"d6EAZyTlRB1pYMzWC9cxsG","rect":[5,5,45,46],"offset":[1,-2],"originalSize":[53,52]}}]