[{"__type__":"cc.SpriteFrame","content":{"name":"joinbg","rect":{"x":0,"y":0,"width":74,"height":91},"offset":{"x":0,"y":0},"originalSize":{"width":74,"height":91},"rotated":false,"capInsets":[27,36,21,30],"texture":"06owfsnZhD0rH4kdbAT1m4@6c48a"}},{"__type__":"cc.SpriteFrame","content":{"name":"infoicon","rect":{"x":0,"y":0,"width":29,"height":29},"offset":{"x":0,"y":0},"originalSize":{"width":29,"height":29},"rotated":false,"capInsets":[0,0,0,0],"texture":"6aBDjBwABBLrMXyeGuPGT5@6c48a"}},{"__type__":"cc.SpriteFrame","content":{"name":"close","rect":{"x":0,"y":0,"width":37,"height":37},"offset":{"x":0,"y":0},"originalSize":{"width":37,"height":37},"rotated":false,"capInsets":[0,0,0,0],"texture":"7dUknXXxtBG72HtIhXVyYH@6c48a"}},[{"__type__":"cc.Prefab","data":{"__id__":1}},{"__type__":"cc.Node","_name":"TournamentDialog","_children":[{"__id__":2}],"_components":[{"__type__":"cc.UITransformComponent","_name":"HomePage<UITransformComponent>","node":{"__id__":1},"_priority":20,"_contentSize":{"__type__":"cc.Size","width":750,"height":1334}},{"__type__":"cc.WidgetComponent","_name":"HomePage<WidgetComponent>","node":{"__id__":1},"_alignFlags":45,"_originalWidth":100,"_originalHeight":100},{"__type__":"855cdd65PtEqI+u50ySOusY","node":{"__id__":1}}],"_prefab":{"__type__":"cc.PrefabInfo","root":{"__id__":1},"asset":{"__id__":0},"fileId":"3dAlXTl2hCFrPDZsiuBjPf","_synced":{"default":false,"serializable":false}}},{"__type__":"cc.Node","_name":"content","_parent":{"__id__":1},"_children":[{"__id__":3},{"__id__":4},{"__id__":5},{"__id__":7},{"__id__":8},{"__id__":9},{"__id__":10},{"__id__":11}],"_components":[{"__type__":"cc.UITransformComponent","_name":"kuang<UITransformComponent>","node":{"__id__":2},"_contentSize":{"__type__":"cc.Size","width":584.16,"height":467.74}},{"__type__":"cc.SpriteComponent","_name":"kuang<SpriteComponent>","node":{"__id__":2},"_spriteFrame":{"__uuid__":"06owfsnZhD0rH4kdbAT1m4@f9941"},"_type":1,"_sizeMode":0},{"__type__":"cc.BlockInputEventsComponent","node":{"__id__":2}}],"_prefab":{"__type__":"cc.PrefabInfo","root":{"__id__":1},"asset":{"__id__":0},"fileId":"07LJkV1zhG/JTJBnDByBdK","_synced":{"default":false,"serializable":false}},"_lpos":{"__type__":"cc.Vec3","y":44.754},"_layer":33554432},{"__type__":"cc.Node","_name":"title","_parent":{"__id__":2},"_components":[{"__type__":"cc.UITransformComponent","node":{"__id__":3},"_contentSize":{"__type__":"cc.Size","width":364.33,"height":50.4}},{"__type__":"cc.LabelComponent","node":{"__id__":3},"_color":{"__type__":"cc.Color"},"_string":"WELCOME TO TOURNAMENT!","_actualFontSize":25,"_fontSize":25,"_isBold":true}],"_prefab":{"__type__":"cc.PrefabInfo","root":{"__id__":1},"asset":{"__id__":0},"fileId":"a9CW9h31ZKrY15sBVYEFVh","_synced":{"default":false,"serializable":false}},"_lpos":{"__type__":"cc.Vec3","y":77.757},"_layer":33554432},{"__type__":"cc.Node","_name":"icon","_parent":{"__id__":2},"_components":[{"__type__":"cc.UITransformComponent","node":{"__id__":4},"_contentSize":{"__type__":"cc.Size","width":93,"height":92}},{"__type__":"cc.SpriteComponent","node":{"__id__":4},"_spriteFrame":{"__uuid__":"e3mwHvySZF6IDKIzHMEKEv@f9941"},"_sizeMode":2}],"_prefab":{"__type__":"cc.PrefabInfo","root":{"__id__":1},"asset":{"__id__":0},"fileId":"70p1MDrORC8IOpnsbxqT8T","_synced":{"default":false,"serializable":false}},"_lpos":{"__type__":"cc.Vec3","y":163.345},"_layer":33554432},{"__type__":"cc.Node","_name":"joinBnt","_parent":{"__id__":2},"_children":[{"__id__":6}],"_components":[{"__type__":"cc.UITransformComponent","node":{"__id__":5},"_contentSize":{"__type__":"cc.Size","width":548.665,"height":72}},{"__type__":"cc.SpriteComponent","node":{"__id__":5},"_spriteFrame":{"__uuid__":"e5KTQ97nNHhJeRPI4p4cRP@f9941"},"_type":1,"_sizeMode":0},{"__type__":"cc.ButtonComponent","node":{"__id__":5},"clickEvents":[{"__type__":"cc.ClickEvent","target":{"__id__":1},"_componentId":"855cdd65PtEqI+u50ySOusY","handler":"onJoin"}],"_transition":3}],"_prefab":{"__type__":"cc.PrefabInfo","root":{"__id__":1},"asset":{"__id__":0},"fileId":"0egwwBqo9MJaCJ81WLfvNw","_synced":{"default":false,"serializable":false}},"_lpos":{"__type__":"cc.Vec3","x":-1.1544999999999987,"y":-176.164},"_layer":33554432},{"__type__":"cc.Node","_name":"fuhuocount","_parent":{"__id__":5},"_components":[{"__type__":"cc.UITransformComponent","node":{"__id__":6},"_contentSize":{"__type__":"cc.Size","width":106.68,"height":50.4}},{"__type__":"cc.LabelComponent","node":{"__id__":6},"_string":"JOIN!","_actualFontSize":40,"_isBold":true}],"_prefab":{"__type__":"cc.PrefabInfo","root":{"__id__":1},"asset":{"__id__":0},"fileId":"2bW5l43+NO7J/ftuu71xg7","_synced":{"default":false,"serializable":false}},"_layer":33554432},{"__type__":"cc.Node","_name":"close","_parent":{"__id__":2},"_components":[{"__type__":"cc.UITransformComponent","node":{"__id__":7},"_contentSize":{"__type__":"cc.Size","width":37,"height":37}},{"__type__":"cc.SpriteComponent","node":{"__id__":7},"_spriteFrame":{"__uuid__":"7dUknXXxtBG72HtIhXVyYH@f9941"},"_sizeMode":2},{"__type__":"cc.ButtonComponent","node":{"__id__":7},"clickEvents":[{"__type__":"cc.ClickEvent","target":{"__id__":1},"_componentId":"855cdd65PtEqI+u50ySOusY","handler":"onClose"}],"_transition":3},{"__type__":"b9529yE3w1KxLeWvJjh3ic+","node":{"__id__":7}}],"_prefab":{"__type__":"cc.PrefabInfo","root":{"__id__":1},"asset":{"__id__":0},"fileId":"b1iPBzbWRGlY5aYmASugjI","_synced":{"default":false,"serializable":false}},"_lpos":{"__type__":"cc.Vec3","x":249.191,"y":194.402},"_layer":33554432},{"__type__":"cc.Node","_name":"info","_parent":{"__id__":2},"_components":[{"__type__":"cc.UITransformComponent","node":{"__id__":8},"_contentSize":{"__type__":"cc.Size","width":29,"height":29}},{"__type__":"cc.SpriteComponent","node":{"__id__":8},"_spriteFrame":{"__uuid__":"6aBDjBwABBLrMXyeGuPGT5@f9941"},"_sizeMode":2}],"_prefab":{"__type__":"cc.PrefabInfo","root":{"__id__":1},"asset":{"__id__":0},"fileId":"919fFrJZRPsZ1hfKt3PoNd","_synced":{"default":false,"serializable":false}},"_lpos":{"__type__":"cc.Vec3","x":-252.331,"y":8.176},"_layer":33554432},{"__type__":"cc.Node","_name":"title-001","_parent":{"__id__":2},"_components":[{"__type__":"cc.UITransformComponent","node":{"__id__":9},"_contentSize":{"__type__":"cc.Size","width":110,"height":50.4}},{"__type__":"cc.LabelComponent","node":{"__id__":9},"_color":{"__type__":"cc.Color","r":99,"g":98,"b":103},"_string":"SHUOMING","_actualFontSize":20,"_fontSize":20,"_isBold":true}],"_prefab":{"__type__":"cc.PrefabInfo","root":{"__id__":1},"asset":{"__id__":0},"fileId":"1caLoVY6RM9aJGT+yCgMdj","_synced":{"default":false,"serializable":false}},"_lpos":{"__type__":"cc.Vec3","x":-150.735,"y":4.078},"_layer":33554432},{"__type__":"cc.Node","_name":"des","_parent":{"__id__":2},"_components":[{"__type__":"cc.UITransformComponent","node":{"__id__":10},"_contentSize":{"__type__":"cc.Size","width":436.31,"height":97.8}},{"__type__":"cc.LabelComponent","node":{"__id__":10},"_color":{"__type__":"cc.Color","r":99,"g":98,"b":103},"_string":"Tournaments and their Leaderboards are\npublic and can be shared by anyone who\nplays.","_horizontalAlign":0,"_actualFontSize":24,"_fontSize":24,"_lineHeight":30}],"_prefab":{"__type__":"cc.PrefabInfo","root":{"__id__":1},"asset":{"__id__":0},"fileId":"50v8M+r45O/oeFfroFG/mQ","_synced":{"default":false,"serializable":false}},"_lpos":{"__type__":"cc.Vec3","x":6.079,"y":-64.979},"_layer":33554432},{"__type__":"cc.Node","_name":"joinsep","_parent":{"__id__":2},"_components":[{"__type__":"cc.UITransformComponent","node":{"__id__":11},"_contentSize":{"__type__":"cc.Size","width":577.79,"height":3}},{"__type__":"cc.SpriteComponent","node":{"__id__":11},"_spriteFrame":{"__uuid__":"cdd0msVkBPwaElFKwyqq/H@f9941"},"_sizeMode":0}],"_prefab":{"__type__":"cc.PrefabInfo","root":{"__id__":1},"asset":{"__id__":0},"fileId":"66pjGszfROdIHIbfdZdOgW","_synced":{"default":false,"serializable":false}},"_lpos":{"__type__":"cc.Vec3","x":-0.28999999999999204,"y":39.673}}],{"__type__":"cc.SpriteFrame","content":{"name":"joinsep","rect":{"x":0,"y":0,"width":27,"height":3},"offset":{"x":0,"y":0},"originalSize":{"width":27,"height":3},"rotated":false,"capInsets":[0,0,0,0],"texture":"cdd0msVkBPwaElFKwyqq/H@6c48a"}},{"__type__":"cc.SpriteFrame","content":{"name":"cup","rect":{"x":0,"y":0,"width":93,"height":92},"offset":{"x":0,"y":0},"originalSize":{"width":93,"height":92},"rotated":false,"capInsets":[0,0,0,0],"texture":"e3mwHvySZF6IDKIzHMEKEv@6c48a"}},{"__type__":"cc.SpriteFrame","content":{"name":"joinbnt","rect":{"x":0,"y":0,"width":59,"height":72},"offset":{"x":0,"y":0},"originalSize":{"width":59,"height":72},"rotated":false,"capInsets":[17,19,16,18],"texture":"e5KTQ97nNHhJeRPI4p4cRP@6c48a"}}]
