[1,["ecpdLyjvZBwrvm+cedCcQy","41D7kWhyFGY7q4NDlzkazn","1bb39797e","fcgAzFUThAbLsItavHmmMS","5bNAyQ6fhI4q+uX1MkHzX9","9cc1n89NZLTYkL8gw1xtj7","abz9YjC5tIl4tIEvYppeuH","db+zz6mKBIc4o9fV28hBjH","36CrNGzu5N24pKk12lM4Pc","53OjRnfv9Dv75iQI1vJtnn","dfd/57AdJAKJSfgxoh4jf7","27tKg7gvJKLocfoOkDnFrq","5bS3AXdrVB3754rLPa9kaG","1aIzfy3YBKWZaIeSezt0NI","6cgDmp0VxFAaxcGSvVPMD+","41jmlvNyVH37GXzExfJZBx","21aXkADhVIEL1q1DO848Yh","66VeglaQ1O3rlXrYUOXqpU","bdENj6D0dEMbdCdJrdkJ8Z","6ch12vx61J/qtm/kBbhlqo","4aHSToEMVGwbukYakdlf3N","ae/K5fQBVPnKtzixt/7yHP","0f7RpoV4JEJYGfckleyZct","177AdK5DNEoZ4WPZ5r65x+","a2QQadx/BGeYNYMz5RUIwE","b1vKxSV2BKC6mwTXGpXa+X","1bf2156c3"],["node","_spriteFrame","_textureSetter","itemPrefab","root","data","_normalMaterial","knifeSprite","goldAppleNode","appleNode","countLabel","spinSwitcher","spinList3","spinList2","spinList1","spinVideoIcon","noVideo","spinBtn","videoBtn","freeVideoBtn","spinTime","videoTime","_N$target","_defaultClip"],[["cc.Node",["_name","_active","_opacity","_prefab","_components","_parent","_contentSize","_trs","_children","_color","_eulerAngles","_anchorPoint"],0,4,9,1,5,7,2,5,5,5],"cc.SpriteFrame",["cc.Sprite",["_sizeMode","_isTrimmedMode","_type","node","_spriteFrame","_materials"],0,1,6,3],["cc.Node",["_name","_parent","_components","_prefab","_trs","_contentSize","_children","_color"],2,1,2,4,7,5,2,5],["cc.Label",["_string","_fontSize","_N$horizontalAlign","_N$verticalAlign","_lineHeight","node","_materials"],-2,1,3],["cc.Widget",["alignMode","_alignFlags","_left","_originalWidth","_originalHeight","node"],-2,1],["cc.PrefabInfo",["fileId","root"],2,1],["cc.Button",["_N$transition","_N$enableAutoGrayEffect","node","clickEvents","_N$normalColor","_N$target"],1,1,9,5,1],["cc.ClickEvent",["_componentId","handler","customEventData","target"],0,1],["cc.AnimationClip",["_name","_duration","curveData"],0],["cc.Prefab",["_name"],2],["cc.Node",["_name","_parent","_children","_components","_prefab","_contentSize","_trs"],2,1,2,12,4,5,7],["5d435+0PXhNaLiuPW2ZekGD",["node","countLabel","appleNode","goldAppleNode","knifeSprite"],3,1,1,1,1,1],["cc.BlockInputEvents",["node"],3,1],["fa9d18MP39ET4DxIKnRmC8s",["node"],3,1],["80764YU74VICIJfeCDse5yO",["node","videoTime","spinTime","freeVideoBtn","videoBtn","spinBtn","noVideo","spinVideoIcon","spinList1","spinList2","spinList3","spinSwitcher"],3,1,1,1,1,1,1,1,1,1,1,1,1],["44a5fMw4uVH/ZRFrnfPLu/r",["node"],3,1],["e2cbf6kW/5Chaal4gt7e9vE",["node"],3,1],["cc.Mask",["_N$alphaThreshold","node","_materials"],2,1,3],["cc.Animation",["node","_clips"],3,1,3],["46cba9yw5JGj58ieXZ7sRBZ",["node","content","lightNode"],3,1,1,1]],[[6,0,1,2],[2,0,3,5,4,2],[2,3,5,4,1],[0,0,5,4,3,9,6,7,2],[0,0,5,4,3,6,7,2],[0,0,5,4,3,6,2],[0,0,5,8,4,3,6,7,2],[4,0,1,2,3,5,6,5],[8,0,1,3,3],[0,0,5,8,3,7,2],[0,0,5,4,3,9,6,7,10,2],[0,0,5,3,2],[3,0,1,2,3,5,4,2],[11,0,1,2,3,4,5,6,2],[2,3,4,1],[20,0,1,2,1],[9,0,1,2,4],[10,0,2],[0,0,5,4,3,6,7,10,2],[0,0,5,4,3,9,6,2],[3,0,1,6,2,3,4,2],[7,0,2,3,4,5,2],[7,1,0,2,3,4,5,3],[0,0,8,4,3,6,2],[0,0,8,4,3,6,7,2],[0,0,5,8,4,3,2],[0,0,1,5,4,3,6,7,3],[0,0,2,5,4,3,9,6,11,7,3],[0,0,5,4,3,6,11,7,2],[3,0,1,2,3,7,5,4,2],[3,0,1,6,2,3,5,4,2],[3,0,1,6,2,3,2],[12,0,1,2,3,4,1],[6,1,1],[2,3,1],[2,0,3,4,2],[2,0,1,3,5,4,3],[2,2,0,3,5,4,3],[4,0,1,2,3,5,5],[4,0,1,4,2,3,5,6,6],[5,0,1,5,3],[5,0,1,2,5,4],[5,0,1,3,4,5,5],[13,0,1],[14,0,1],[15,0,1,2,3,4,5,6,7,8,9,10,11,1],[16,0,1],[17,0,1],[8,0,1,2,3,4],[18,0,1,2,2],[19,0,1,1]],[[[[16,"resultspinback",0.16666666666666666,{"paths":{"qiu":{"props":{"y":[{"frame":0,"value":-76},{"frame":0.16666666666666666,"value":19}]}},"gan":{"props":{"scaleY":[{"frame":0,"value":-1},{"frame":0.16666666666666666,"value":1}]}}}}]],0,0,[],[],[]],[[{"name":"slotoshadow","rect":[802,86,223,77],"offset":[0,0],"originalSize":[223,77],"rotated":1,"capInsets":[0,0,0,0]}],[1],0,[0],[2],[2]],[[{"name":"knife_20","rect":[15,7,34,178],"offset":[1,4],"originalSize":[62,200],"capInsets":[0,0,0,0]}],[1],0,[0],[2],[10]],[[{"name":"gan","rect":[864,3,10,36],"offset":[-0.5,0.5],"originalSize":[13,39],"capInsets":[0,0,0,0]}],[1],0,[0],[2],[2]],[[[16,"resultslot",0.16666666666666666,{"paths":{"qiu/slotovideo":{"props":{}},"gan":{"props":{"scaleY":[{"frame":0,"value":1},{"frame":0.16666666666666666,"value":-1}]}},"qiu":{"props":{"y":[{"frame":0,"value":19},{"frame":0.16666666666666666,"value":-76}]}}}}]],0,0,[],[],[]],[[[17,"SlotItem"],[23,"SlotItem",[-7,-8,-9,-10,-11],[[32,-6,-5,-4,-3,-2]],[0,"65QU9cDMtNIrMg1BwGvaSD",-1],[5,70,90]],[18,"apple",1,[[14,-12,0]],[0,"c6hBTvAadFmoWPbR3w3hZT",1],[5,36,41],[0,17,0,0,0,0,1,0.9,0.9,1],[1,0,0,-180]],[18,"jinpinguo",1,[[14,-13,1]],[0,"57324UoptIj7uyag/MEE5F",1],[5,129,136],[0,15.2,0,0,0,0,1,0.25,0.25,1],[1,0,0,-180]],[29,"label",1,[-14],[0,"d1cddH/doRNQ4Aodz8556bh",1],[4,4282869247],[5,28,40],[0,-18,0,0,0,0,1,1,1,1]],[38,"20",25,1,1,4],[12,"knife",1,[-15],[0,"dfUk3zLRJMFKVdtV6tgjjd",1],[5,34,178],[0,0,0,0,0,0,1,0.4,0.4,1]],[34,6],[4,"line",1,[[35,0,-16,2]],[0,"12tn7IGZBLeaZ2tCrT7nTA",1],[5,72,4],[0,-49,0,0,0,0,1,1,1,1]]],0,[0,4,1,0,7,7,0,8,3,0,9,2,0,10,5,0,0,1,0,-1,2,0,-2,4,0,-3,3,0,-4,6,0,-5,8,0,0,2,0,0,3,0,-1,5,0,-1,7,0,0,8,0,5,1,16],[0,0,0,7],[1,1,1,1],[5,11,12,13]],[[{"name":"slotline","rect":[507,298,75,4],"offset":[0,0],"originalSize":[75,4],"rotated":1,"capInsets":[0,0,0,0]}],[1],0,[0],[2],[2]],[[[17,"IosShopPage"],[24,"IosShopPage",[-18,-19,-20],[[40,0,45,-2],[43,-3],[44,-4],[45,-16,-15,-14,-13,-12,-11,-10,-9,-8,-7,-6,-5],[46,-17]],[33,-1],[5,640,1136],[320,568,0,0,0,0,1,1,1,1]],[25,"content",1,[-22,-23,-24,-25,-26,-27,-28,-29,-30,-31,-32,-33,-34,-35,-36,-37],[[47,-21]],[0,"37+4UYJPtNzoKpiVHL+Dew",1]],[13,"sloto",2,[-40,-41,-42,-43,-44],[[[2,-38,[77],78],-39],4,1],[0,"63oeEw/lFFkYEX2jCi0TTL",1],[5,277,99],[0,-363.697,0,0,0,0,1,1.1,1.1,0]],[4,"fanhui",1,[[36,0,false,-45,[2],3],[21,3,-47,[[8,"fa9d18MP39ET4DxIKnRmC8s","playClick",1],[48,"44a5fMw4uVH/ZRFrnfPLu/r","closeDialog","IosShopPage",1]],[4,4292269782],-46],[41,0,8,6.5,-48]],[0,"6ePfG8YPhFKL4k/HURVPJh",1],[5,71,78],[-278,490,0,0,0,0,1,1,1,0]],[13,"shopvideo",2,[-51],[[[1,0,-49,[44],45],-50],4,1],[0,"8682WyKZFKR4LcmkwyREMK",1],[5,200,103],[147,176.154,0,0,0,0,1,1,1,0]],[6,"light",2,[-53,-54,-55],[[2,-52,[51],52]],[0,"e8iJn+ofJLQqyov45FNU3N",1],[5,208,212],[-142,-87.255,0,0,0,0,1,1,1,1]],[13,"shopvideotime",2,[-58],[[[1,0,-56,[55],56],-57],4,1],[0,"d6nJqxm8FJ9KfOHd1GY6eh",1],[5,200,103],[147,-82.255,0,0,0,0,1,1,1,0]],[6,"content",3,[-60,-61,-62],[[49,1,-59,[71]]],[0,"ccDlQ1xTRAoJLCsUeMviqm",1],[5,224,77],[-14,-1,0,0,0,0,1,1,1,1]],[9,"lineGroup1",2,[-63,-64,-65],[0,"d4V8GLElNFjZwMrYMASLPS",1],[0,305.557,0,0,0,0,1,1,1,1]],[9,"lineGroup2",2,[-66,-67,-68],[0,"e3YmrHeWFBsaFbRTvTsvzy",1],[0,34.352,0,0,0,0,1,1,1,1]],[9,"lineGroup3",2,[-69,-70,-71],[0,"bfZiZhXhVPmLne6/stnGJa",1],[0,-236.732,0,0,0,0,1,1,1,1]],[6,"light",2,[-73,-74],[[2,-72,[40],41]],[0,"26xYLQlldF54akKc4PLo0a",1],[5,208,212],[-142,181.154,0,0,0,0,1,1,1,1]],[30,"slotobar",3,[-76,-77],[-75],[0,"32k+ROixtK2YYcBc8ENops",1],[5,28,60],[131,28,0,0,0,0,1,1,1,1]],[20,"Slotlist",8,[-79,-80],[-78],[0,"9eTrb+OuBKIJSph/cq3lBI",1],[-75.6,0,0,0,0,0,1,1,1,1]],[31,"Slotlist",8,[-82,-83],[-81],[0,"1b2LdU3KJO9YUoaL8hN51q",1]],[20,"Slotlist",8,[-85,-86],[-84],[0,"2cfvUhP2ZAmbYxESm1B9fa",1],[75,0,0,0,0,0,1,1,1,1]],[5,"black",1,[[1,0,-87,[0],1],[42,0,45,2,2,-88]],[0,"415ZYycQZOgLCf1GcrDYTm",1],[5,640,1136]],[6,"poweruptitle",2,[-90],[[2,-89,[33],34]],[0,"2a++7/cMpCs5fv8kf40Bj9",1],[5,451,62],[0,440,0,0,0,0,1,1,1,1]],[6,"jinbi",12,[-92],[[2,-91,[38],39]],[0,"80E19b6CVCQ5nRPH5SGOUs",1],[5,37,39],[-39.717,-81.359,0,0,0,0,1,1,1,1]],[19,"light",14,[[1,0,-93,[65],66]],[0,"ffgnM71kZLZ5EC+n0JLMfX",1],[4,4290117375],[5,72,76]],[3,"light",15,[[1,0,-94,[67],68]],[0,"62ri69pANE8onbJrXstWtY",1],[4,4290117375],[5,73,76],[-0.7,0,0,0,0,0,1,1,1,1]],[19,"light",16,[[1,0,-95,[69],70]],[0,"46ypTKDQ1Kzb4Dka0PjwA8",1],[4,4290117375],[5,74,76]],[3,"guangao",3,[[2,-96,[72],73]],[0,"1dcd18ilZC4KW33G4ae8s3",1],[4,4281040628],[5,64,48],[-89.6,-1.1,0,0,0,0,1,0.7,0.7,1]],[26,"slotonovideo",false,3,[[14,-97,76]],[0,"491REictJO/LNIBUNwQvPZ",1],[5,228,81],[-14,-1,0,0,0,0,1,1,1,1]],[27,"titlebg",100,2,[[37,1,0,-98,[4],5]],[0,"930eSi5htLlZAwfxj0J7Rw",1],[4,4278190080],[5,600,980],[0,0.5,1],[0,437,0,0,0,0,1,1,1,1]],[3,"bg1",2,[[1,0,-99,[6],7]],[0,"f8xpDq819Mh5xE79EIaUUw",1],[4,4287459633],[5,530,230],[0,171,0,0,0,0,1,1,1,1]],[3,"bg2",2,[[1,0,-100,[8],9]],[0,"5bx8Om9/5Ny7v96mc7oHjd",1],[4,4287459633],[5,530,230],[0,-100,0,0,0,0,1,1,1,1]],[3,"bg3",2,[[1,0,-101,[10],11]],[0,"32VrXtdP5Hsqb48w/wyZWZ",1],[4,4287459633],[5,530,230],[0,-371,0,0,0,0,1,1,1,1]],[3,"line",9,[[1,0,-102,[12],13]],[0,"a5tiBTHBhEf7LjavIzYzuS",1],[4,4292190783],[5,230,3],[-150,0,0,0,0,0,1,1,1,1]],[3,"line",9,[[1,0,-103,[14],15]],[0,"35cUE8HGpJYopgpUFQS26E",1],[4,4292190783],[5,230,3],[150,0,0,0,0,0,1,1,1,1]],[10,"line",9,[[1,0,-104,[16],17]],[0,"27CFjkqbBK9qG29dSIov5u",1],[4,4292190783],[5,20,20],[0,0,0,0,0,0.3826834323650898,0.9238795325112867,1,1,1],[1,0,0,45]],[3,"line",10,[[1,0,-105,[18],19]],[0,"c4cQwMwcVHGpSQIDvps/4p",1],[4,4292190783],[5,230,3],[-150,0,0,0,0,0,1,1,1,1]],[3,"line",10,[[1,0,-106,[20],21]],[0,"4cMEUVQlRCpayeB75lEzIe",1],[4,4292190783],[5,230,3],[150,0,0,0,0,0,1,1,1,1]],[10,"line",10,[[1,0,-107,[22],23]],[0,"62cfDseGBJ3aDabrBExDZT",1],[4,4292190783],[5,20,20],[0,0,0,0,0,0.3826834323650898,0.9238795325112867,1,1,1],[1,0,0,45]],[3,"line",11,[[1,0,-108,[24],25]],[0,"bdBFvxm8ZKR6Ga+rmPjnFR",1],[4,4292190783],[5,230,3],[-150,0,0,0,0,0,1,1,1,1]],[3,"line",11,[[1,0,-109,[26],27]],[0,"34fEilQuhP5Yzzbl7EiI7O",1],[4,4292190783],[5,230,3],[150,0,0,0,0,0,1,1,1,1]],[10,"line",11,[[1,0,-110,[28],29]],[0,"7bSb8TGNlHfbcs/NqztxST",1],[4,4292190783],[5,20,20],[0,0,0,0,0,0.3826834323650898,0.9238795325112867,1,1,1],[1,0,0,45]],[4,"apple",2,[[2,-111,[30],31]],[0,"2bcgmE23tIaZIFQjNzvKge",1],[5,36,41],[0,362.264,0,0,0,0,1,1.2,-1.2,1]],[5,"title",18,[[39,"商店",34,34,1,1,-112,[32]]],[0,"b3tf8aH4xDcpsr7qX5wVIE",1],[5,68,42.84]],[5,"packageapple",12,[[2,-113,[35],36]],[0,"c9sQZV+NVDg6JONo+TXBHV",1],[5,115,107]],[4,"label",19,[[7,"x 200",35,1,1,-114,[37]]],[0,"4ffpiIg1RDKa6bIw7ko29B",1],[5,85.62,50.4],[67.793,0,0,0,0,0,1,1,1,1]],[5,"guanggao",5,[[2,-115,[42],43]],[0,"ec/SwSVIZNc5aOX0sqIFkH",1],[5,64,48]],[22,true,3,5,[[8,"80764YU74VICIJfeCDse5yO","onVideoClicked",1]],[4,4292269782],5],[5,"boxapple",6,[[2,-116,[46],47]],[0,"e71n8685FK07PXZ/MnXVnk",1],[5,101,124]],[4,"jinbi",6,[[2,-117,[48],49]],[0,"1euNHAbkdN7JhfbJIosvqp",1],[5,37,39],[-37,-94.598,0,0,0,0,1,1,1,1]],[4,"label",6,[[7,"x 400",35,1,1,-118,[50]]],[0,"74HNVH4LRAkKd2JueWbRVr",1],[5,85.62,50.4],[30.554,-94.598,0,0,0,0,1,1,1,1]],[5,"guanggao",7,[[2,-119,[53],54]],[0,"f9nBrj5rtBPrzWNgJ6FvUn",1],[5,64,48]],[22,true,3,7,[[8,"80764YU74VICIJfeCDse5yO","onTimedVideoClicked",1]],[4,4292269782],7],[12,"videotime",2,[-120],[0,"b9Gl5aWLZE96YaiNAZMA29",1],[5,75.07,50.4],[144,-164.255,0,0,0,0,1,1,1,1]],[7,"12:12",30,1,1,49,[57]],[12,"videotime",2,[-121],[0,"42jGvLc1NG+4p55A7qcbOw",1],[5,75.07,50.4],[0,-449.846,0,0,0,0,1,1,1,1]],[7,"12:12",30,1,1,51,[58]],[28,"gan",13,[[2,-122,[59],60]],[0,"e73A/xFlxJQZLJXFoOUvD3",1],[5,10,36],[0,0.5,0],[1,-29,0,0,0,0,1,1,1,1]],[4,"qiu",13,[[2,-123,[61],62]],[0,"14f+fPx4ZDbJnn5Gz4FTEO",1],[5,28,28],[0.9,16.7,0,0,0,0,1,1,1,1]],[50,13,[63,64]],[11,"content",14,[0,"7ak8ibsUFKBI+D5SmUJ2+Z",1]],[15,14,56,20],[11,"content",15,[0,"7aUGvF+d5M2pPYVcQWh9Fr",1]],[15,15,58,21],[11,"content",16,[0,"61kfmuP8RAi6my67wkuR3z",1]],[15,16,60,22],[4,"slotoshadow",3,[[2,-124,[74],75]],[0,"3aMZyP8mRE86E9G18DXlDz",1],[5,223,77],[-14,-1,0,0,0,0,1,1,1,1]],[21,3,3,[[8,"80764YU74VICIJfeCDse5yO","onSpinClicked",1]],[4,4292269782],3]],0,[0,4,1,0,0,1,0,0,1,0,0,1,0,11,55,0,12,61,0,13,59,0,14,57,0,15,23,0,16,24,0,17,63,0,18,48,0,19,43,0,20,52,0,21,50,0,0,1,0,0,1,0,-1,17,0,-2,4,0,-3,2,0,0,2,0,-1,25,0,-2,26,0,-3,27,0,-4,28,0,-5,9,0,-6,10,0,-7,11,0,-8,38,0,-9,18,0,-10,12,0,-11,5,0,-12,6,0,-13,7,0,-14,49,0,-15,51,0,-16,3,0,0,3,0,-2,63,0,-1,13,0,-2,8,0,-3,23,0,-4,62,0,-5,24,0,0,4,0,22,4,0,0,4,0,0,4,0,0,5,0,-2,43,0,-1,42,0,0,6,0,-1,44,0,-2,45,0,-3,46,0,0,7,0,-2,48,0,-1,47,0,0,8,0,-1,14,0,-2,15,0,-3,16,0,-1,29,0,-2,30,0,-3,31,0,-1,32,0,-2,33,0,-3,34,0,-1,35,0,-2,36,0,-3,37,0,0,12,0,-1,40,0,-2,19,0,-1,55,0,-1,53,0,-2,54,0,-1,57,0,-1,20,0,-2,56,0,-1,59,0,-1,21,0,-2,58,0,-1,61,0,-1,22,0,-2,60,0,0,17,0,0,17,0,0,18,0,-1,39,0,0,19,0,-1,41,0,0,20,0,0,21,0,0,22,0,0,23,0,0,24,0,0,25,0,0,26,0,0,27,0,0,28,0,0,29,0,0,30,0,0,31,0,0,32,0,0,33,0,0,34,0,0,35,0,0,36,0,0,37,0,0,38,0,0,39,0,0,40,0,0,41,0,0,42,0,0,44,0,0,45,0,0,46,0,0,47,0,-1,50,0,-1,52,0,0,53,0,0,54,0,0,62,0,5,1,124],[0,0,0,0,0,0,0,0,0,0,0,0,0,0,0,0,0,0,0,0,0,0,0,0,0,0,0,0,0,0,0,0,0,0,0,0,0,0,0,0,0,0,0,0,0,0,0,0,0,0,0,0,0,0,0,0,0,0,0,0,0,0,0,0,0,0,0,0,0,0,0,0,0,0,0,0,0,0,0,43,48,55,57,59,61],[-1,1,-1,1,-1,1,-1,1,-1,1,-1,1,-1,1,-1,1,-1,1,-1,1,-1,1,-1,1,-1,1,-1,1,-1,1,-1,1,-1,-1,1,-1,1,-1,-1,1,-1,1,-1,1,-1,1,-1,1,-1,1,-1,-1,1,-1,1,-1,1,-1,-1,-1,1,-1,1,-1,-2,-1,1,-1,1,-1,1,-1,-1,1,-1,1,1,-1,1,6,6,23,3,3,3],[0,14,0,15,0,16,0,1,0,1,0,1,0,1,0,1,0,1,0,1,0,1,0,1,0,1,0,1,0,1,0,5,0,0,17,0,18,0,0,6,0,7,0,3,0,8,0,19,0,6,0,0,7,0,3,0,8,0,0,0,20,0,21,9,22,0,1,0,1,0,1,0,0,3,0,23,24,0,25,0,0,9,4,4,4]],[[{"name":"slotonovideo","rect":[411,334,228,81],"offset":[0,0],"originalSize":[228,81],"rotated":1,"capInsets":[0,0,0,0]}],[1],0,[0],[2],[2]],[[{"name":"qiu","rect":[450,989,28,28],"offset":[0.5,0.5],"originalSize":[31,31],"capInsets":[0,0,0,0]}],[1],0,[0],[2],[2]],[[{"name":"sloto","rect":[519,69,277,99],"offset":[0,0],"originalSize":[277,99],"capInsets":[0,0,0,0]}],[1],0,[0],[2],[2]],[[{"name":"light","rect":[216,2,208,212],"offset":[0,0],"originalSize":[208,212],"capInsets":[0,0,0,0]}],[1],0,[0],[2],[26]]]]